tests
humus
