Metadata-Version: 1.0
Name: Humus
Version: 0.2.0
Summary: A simple S3 backup script
Home-page: https://github.com/SeanOC/humus
Author: Sean O'Connor
Author-email: sean@saaspire.com
License: MIT
Keywords: amazon aws s3 backup
Platform: UNKNOWN
Classifier: Development Status :: 4 - Beta
Classifier: Environment :: Console
Classifier: Intended Audience :: System Administrators
Classifier: License :: OSI Approved :: MIT License
Classifier: Topic :: System :: Archiving :: Backup
